odoo/addons/l10n_es_igic/README.rst
odoo/addons/l10n_es_igic/__init__.py
odoo/addons/l10n_es_igic/__manifest__.py
odoo/addons/l10n_es_igic/data/template/account.account-es_assoc_canary.csv
odoo/addons/l10n_es_igic/data/template/account.account-es_common_canary.csv
odoo/addons/l10n_es_igic/data/template/account.account-es_full_canary.csv
odoo/addons/l10n_es_igic/data/template/account.account-es_pymes_canary.csv
odoo/addons/l10n_es_igic/data/template/account.fiscal.position-es_common.csv
odoo/addons/l10n_es_igic/data/template/account.tax-es_common_canary.csv
odoo/addons/l10n_es_igic/data/template/account.tax.group-es_common.csv
odoo/addons/l10n_es_igic/i18n/es.po
odoo/addons/l10n_es_igic/i18n/l10n_es_igic.pot
odoo/addons/l10n_es_igic/migrations/17.0.2.1.0/pre-migration.py
odoo/addons/l10n_es_igic/models/__init__.py
odoo/addons/l10n_es_igic/models/template_es_canary.py
odoo/addons/l10n_es_igic/readme/CONTRIBUTORS.md
odoo/addons/l10n_es_igic/readme/DESCRIPTION.md
odoo/addons/l10n_es_igic/readme/INSTALL.md
odoo/addons/l10n_es_igic/static/description/icon.png
odoo/addons/l10n_es_igic/static/description/index.html
odoo_addon_l10n_es_igic-17.0.2.1.2.2.dist-info/METADATA
odoo_addon_l10n_es_igic-17.0.2.1.2.2.dist-info/WHEEL
odoo_addon_l10n_es_igic-17.0.2.1.2.2.dist-info/top_level.txt
odoo_addon_l10n_es_igic-17.0.2.1.2.2.dist-info/RECORD
