Metadata-Version: 2.1
Name: odoo-addon-l10n_es_igic
Version: 17.0.2.1.2.2
Requires-Python: >=3.10
Requires-Dist: odoo>=17.0a,<17.1dev
Summary: IGIC (Impuesto General Indirecto Canario)
Home-page: https://github.com/OCA/l10n-spain
License: AGPL-3
Author: =?utf-8?q?David_Diz_Mart=C3=ADnez=2CAtlantux_Consultores_-_Enrique_Zanardi=2CSistemas_de_Datos=2CComunitea=2CMois=C3=A9s_Fargnoli=2COdoo_Community_Association_=28OCA=29?=
Author-email: support@odoo-community.org
Classifier: Programming Language :: Python
Classifier: Framework :: Odoo
Classifier: Framework :: Odoo :: 17.0
Classifier: License :: OSI Approved :: GNU Affero General Public License v3
